kaggleBuddy/__init__.py
kaggleBuddy/playGround.py
kaggleBuddy/data_exploration/__init__.py
kaggleBuddy/data_exploration/k_data_exploration.py
kaggleBuddy/ensemble/__init__.py
kaggleBuddy/ensemble/k_ensemble.py
kaggleBuddy/exploration/__init__.py
kaggleBuddy/exploration/k_data_exploration.py
kaggleBuddy/exploration/method.py
kaggleBuddy/nn/__init__.py
kaggleBuddy/nn/base.py
kaggleBuddy/nn/cv.py
kaggleBuddy/nn/lr_scheduler.py
kaggleBuddy/nn/nlp.py
kaggleBuddy/nn/nn_helper.py
kaggleBuddy/preprocessing/__init__.py
kaggleBuddy/preprocessing/k_encoder.py
kaggleBuddy/preprocessing/k_feature_select.py
kaggleBuddy/preprocessing/k_new_features.py
kaggleBuddy/preprocessing/new_features.py
kaggleBuddy/utils/__init__.py
kaggleBuddy/utils/data.py
kaggleBuddy/utils/helper.py
kaggleBuddy/utils/image.py
kaggleBuddy/utils/nn.py
kaggleBuddy/utils/plot.py
kaggleBuddy/utils/utils.py
kagglebuddy-0.0.29.dist-info/LICENSE
kagglebuddy-0.0.29.dist-info/METADATA
kagglebuddy-0.0.29.dist-info/WHEEL
kagglebuddy-0.0.29.dist-info/top_level.txt
kagglebuddy-0.0.29.dist-info/RECORD
