Metadata-Version: 2.1
Name: kagglebuddy
Version: 0.0.29
Summary: machine learning toolkit
Home-page: https://github.com/NickYi1990/kaggleBuddy
Author: 鲲(China)
Author-email: 972775099@qq.com
License: UNKNOWN
Platform: UNKNOWN
Classifier: Programming Language :: Python :: 3
Classifier: License :: OSI Approved :: MIT License
Classifier: Operating System :: OS Independent
Requires-Dist: pandas-summary (>=0.0.5)
